sotabench/__init__.py
sotabench/core/__init__.py
sotabench/core/results.py
sotabench-0.0.4.dist-info/LICENSE
sotabench-0.0.4.dist-info/METADATA
sotabench-0.0.4.dist-info/WHEEL
sotabench-0.0.4.dist-info/top_level.txt
sotabench-0.0.4.dist-info/RECORD
