Metadata-Version: 2.1
Name: sotabench
Version: 0.0.4
Summary: Easily benchmark Machine Learning models on selected tasks and datasets
Home-page: https://sotabench.com
Maintainer: rstojnic
License: Apache 2.0
Platform: UNKNOWN
